corpusshow/__init__.py
corpusshow/corpus_cluster.py
corpusshow/example.py
corpusshow-0.1.8.dist-info/LICENSE
corpusshow-0.1.8.dist-info/METADATA
corpusshow-0.1.8.dist-info/WHEEL
corpusshow-0.1.8.dist-info/top_level.txt
corpusshow-0.1.8.dist-info/RECORD
