Metadata-Version: 2.1
Name: corpusshow
Version: 0.1.8
Summary: Corpus-Show makes it easier and faster to visualize corpus through sentence embedding of corpus.
Home-page: https://github.com/DSDanielPark/corpus-show
Author: parkminwoo
Author-email: parkminwoo1991@gmail.com
Requires-Python: >=3.6
License-File: LICENSE
Requires-Dist: transformers
Requires-Dist: tokenizer
Requires-Dist: sentence-transformers
Requires-Dist: quickshow (>=0.1.12)
Requires-Dist: matplotlib (>=3.4.3)
